{
  "law_id": "01-2021-QH15",
  "title": "Luật sửa đổi Phụ lục Danh mục chỉ tiêu thống kê quốc gia tại Luật Thống kê",
  "date": "2021-11-12",
  "loai_van_ban": "LUẬT",
  "linh_vuc": "SỬA ĐỔI, BỔ SUNG MỘT SỐ ĐIỀU VÀ PHỤ LỤC DANH MỤC CHỈ TIÊU THỐNGKÊQUỐC GIA CỦA LUẬTTHỐNGKÊ",
  "noi_dung": [
    {
      "chuong": null,
      "dieu": "Điều 1. Sửa đổi, bổ sung một số điều và Phụ lục Danh mục chỉ tiêu thống kê quốc gia của Luật Thống kê",
      "noi_dung": "1. Sửa đổi, bổ sungKhoản 6 Điều 17như sau:“6. Bộ trưởng Bộ Kế hoạch và Đầu tư chủ trì, phối hợp với bộ, ngành và địa phương thực hiện các nhiệm vụ sau đây:\n2. Sửa đổi, bổ sungĐiểm d Khoản 2 Điều 48như sau:“d) Người đứng đầu cơ quan thống kê cấp tỉnh công bố thông tin thống kê thuộc hệ thống chỉ tiêu thống kê cấp tỉnh, cấp huyện, cấp xã; đối với thông tin thống kê của chỉ tiêu thống kê cấp tỉnh là phân tổ của chỉ tiêu thống kê quốc gia phải thống nhất về chuyên môn, nghiệp vụ với cơ quan thống kê trung ương trước khi công bố.”.\n3. Thay thếPhụ lụcDanh mục chỉ tiêu thống kê quốc gia ban hành kèm theo Luật Thống kê số89/2015/QH13bằngPhụ  lụcDanh mục chỉ tiêu thống kê quốc gia ban hành kèm theo Luật này."
    },
    {
      "chuong": null,
      "dieu": "Điều 2. Điều khoản thi hành",
      "noi_dung": "1. Luật này có hiệu lực thi hành từ ngày 01 tháng 01 năm 2022.\n2. Chương trình điều tra thống kê quốc gia, chế độ báo cáo thống kê cấp quốc gia phục vụ biên soạn các chỉ tiêu thống kê quy định tạiPhụ lụcDanh mục chỉ tiêu thống kê quốc gia ban hành kèm theo Luật Thống kê số89/2015/QH13được tiếp tục thực hiện đến hết ngày 31 tháng 12 năm 2022.Luật này được Quốc hội nước Cộng hòa xã hội chủ nghĩa Việt Nam khoá XV, kỳ họp thứ 2 thông qua ngày 12 tháng 11 năm 2021."
    }
  ]
}